jacket123.py
jacket123-0.1.0.dist-info/METADATA
jacket123-0.1.0.dist-info/WHEEL
jacket123-0.1.0.dist-info/top_level.txt
jacket123-0.1.0.dist-info/RECORD
