Metadata-Version: 2.1
Name: jacket123
Version: 0.1.0
Summary: This is a module which can create operations like plus and minus
Author: Someone
Author-email: someone@someone.com
